{"cameraMode":{"drawMode":0,"name":"Shaded","section":"Shading Mode"},"sceneLighting":false,"audioPlay":false,"sceneViewState":{"m_AlwaysRefresh":false,"showFog":true,"showSkybox":false,"showFlares":true,"showImageEffects":true,"showParticleSystems":true,"showVisualEffectGraphs":true,"m_FxEnabled":true},"in2DMode":false,"pivot":{"x":-4.228795528411865,"y":-0.8332006335258484,"z":-5.8098578453063969},"rotation":{"x":0.05974895507097244,"y":-0.1313830018043518,"z":0.007931924425065518,"w":0.9895017743110657},"size":4.042788982391357,"orthographic":false}